Unifile-0.1.1.dist-info/DESCRIPTION.rst
Unifile-0.1.1.dist-info/METADATA
Unifile-0.1.1.dist-info/RECORD
Unifile-0.1.1.dist-info/WHEEL
Unifile-0.1.1.dist-info/metadata.json
Unifile-0.1.1.dist-info/top_level.txt
unifile/__init__.py
unifile/dump.py
unifile/otevrit.py
