Metadata-Version: 2.0
Name: Unifile
Version: 0.1.1
Summary: For save settings or file load dump data
Home-page: https://github.com/heavyblack1/unifile
Author: heavyblack
Author-email: heavyblack1@gmail.com
License: GNU v3
Project-URL: Source Code, https://github.com/heavyblack1/unifile
Keywords: file yaml json txt
Platform: UNKNOWN
Classifier: License :: OSI Approved :: GNU General Public License v3 (GPLv3)
Classifier: Programming Language :: Python
Classifier: Programming Language :: Python :: 3
Classifier: Programming Language :: Python :: 3.7
Classifier: Topic :: Software Development :: Libraries :: Python Modules
Requires-Dist: pyaml
Requires-Dist: pandas
Requires-Dist: PyPDF2
Requires-Dist: openpyxl
